ccxt_1_56_19/__init__.py
ccxt_1_56_19/aax.py
ccxt_1_56_19/aofex.py
ccxt_1_56_19/ascendex.py
ccxt_1_56_19/bequant.py
ccxt_1_56_19/bibox.py
ccxt_1_56_19/bigone.py
ccxt_1_56_19/binance.py
ccxt_1_56_19/binancecoinm.py
ccxt_1_56_19/binanceus.py
ccxt_1_56_19/binanceusdm.py
ccxt_1_56_19/bit2c.py
ccxt_1_56_19/bitbank.py
ccxt_1_56_19/bitbay.py
ccxt_1_56_19/bitbns.py
ccxt_1_56_19/bitcoincom.py
ccxt_1_56_19/bitfinex.py
ccxt_1_56_19/bitfinex2.py
ccxt_1_56_19/bitflyer.py
ccxt_1_56_19/bitforex.py
ccxt_1_56_19/bitget.py
ccxt_1_56_19/bithumb.py
ccxt_1_56_19/bitmart.py
ccxt_1_56_19/bitmex.py
ccxt_1_56_19/bitpanda.py
ccxt_1_56_19/bitso.py
ccxt_1_56_19/bitstamp.py
ccxt_1_56_19/bitstamp1.py
ccxt_1_56_19/bittrex.py
ccxt_1_56_19/bitvavo.py
ccxt_1_56_19/bitz.py
ccxt_1_56_19/bl3p.py
ccxt_1_56_19/braziliex.py
ccxt_1_56_19/btcalpha.py
ccxt_1_56_19/btcbox.py
ccxt_1_56_19/btcmarkets.py
ccxt_1_56_19/btctradeua.py
ccxt_1_56_19/btcturk.py
ccxt_1_56_19/buda.py
ccxt_1_56_19/bw.py
ccxt_1_56_19/bybit.py
ccxt_1_56_19/cdax.py
ccxt_1_56_19/cex.py
ccxt_1_56_19/coinbase.py
ccxt_1_56_19/coinbaseprime.py
ccxt_1_56_19/coinbasepro.py
ccxt_1_56_19/coincheck.py
ccxt_1_56_19/coinegg.py
ccxt_1_56_19/coinex.py
ccxt_1_56_19/coinfalcon.py
ccxt_1_56_19/coinfloor.py
ccxt_1_56_19/coinmarketcap.py
ccxt_1_56_19/coinmate.py
ccxt_1_56_19/coinone.py
ccxt_1_56_19/coinspot.py
ccxt_1_56_19/crex24.py
ccxt_1_56_19/currencycom.py
ccxt_1_56_19/delta.py
ccxt_1_56_19/deribit.py
ccxt_1_56_19/digifinex.py
ccxt_1_56_19/eqonex.py
ccxt_1_56_19/equos.py
ccxt_1_56_19/exmo.py
ccxt_1_56_19/exx.py
ccxt_1_56_19/flowbtc.py
ccxt_1_56_19/ftx.py
ccxt_1_56_19/gateio.py
ccxt_1_56_19/gemini.py
ccxt_1_56_19/hbtc.py
ccxt_1_56_19/hitbtc.py
ccxt_1_56_19/hollaex.py
ccxt_1_56_19/huobi.py
ccxt_1_56_19/huobijp.py
ccxt_1_56_19/huobipro.py
ccxt_1_56_19/idex.py
ccxt_1_56_19/independentreserve.py
ccxt_1_56_19/indodax.py
ccxt_1_56_19/itbit.py
ccxt_1_56_19/kraken.py
ccxt_1_56_19/kucoin.py
ccxt_1_56_19/kuna.py
ccxt_1_56_19/latoken.py
ccxt_1_56_19/lbank.py
ccxt_1_56_19-1.56.19.dist-info/LICENSE
ccxt_1_56_19-1.56.19.dist-info/METADATA
ccxt_1_56_19-1.56.19.dist-info/WHEEL
ccxt_1_56_19-1.56.19.dist-info/top_level.txt
ccxt_1_56_19-1.56.19.dist-info/RECORD
